real_estate_model/__init__.py
real_estate_model/config.py
real_estate_model/config.yml
real_estate_model/predict.py
real_estate_model/train.py
real_estate_model/trained_models/lgb_model.txt
RealEstate_package-1.5.0.dist-info/METADATA
RealEstate_package-1.5.0.dist-info/WHEEL
RealEstate_package-1.5.0.dist-info/top_level.txt
RealEstate_package-1.5.0.dist-info/RECORD
