Metadata-Version: 2.1
Name: RealEstate-package
Version: 1.5.0
Summary: МЛ-модель, предсказывающая стоимость недвижимости по её параметрам.
Home-page: https://github.com/Lada-Rom/RealEstate_package
Author: Клейменов А., Толстенко Л.
Author-email: notmy@gmail.com
License: BSD-3
Project-URL: Documentation, https://github.com/Lada-Rom/RealEstate_package
Keywords: lightgbm python real_estate price
Platform: UNKNOWN
Classifier: Programming Language :: Python :: 3.8
Classifier: License :: OSI Approved :: MIT License
Classifier: Operating System :: OS Independent
Requires-Python: >=3.7
Requires-Dist: anyio (==3.6.2)
Requires-Dist: click (==8.1.3)
Requires-Dist: fastapi (==0.95.2)
Requires-Dist: h11 (==0.14.0)
Requires-Dist: idna (==3.4)
Requires-Dist: joblib (==1.2.0)
Requires-Dist: lightgbm (==3.3.5)
Requires-Dist: numpy (==1.24.3)
Requires-Dist: pandas (==2.0.1)
Requires-Dist: pydantic (==1.10.7)
Requires-Dist: python-dateutil (==2.8.2)
Requires-Dist: pytz (==2023.3)
Requires-Dist: scikit-learn (==1.2.2)
Requires-Dist: scipy (==1.10.1)
Requires-Dist: six (==1.16.0)
Requires-Dist: sniffio (==1.3.0)
Requires-Dist: starlette (==0.27.0)
Requires-Dist: strictyaml (==1.7.3)
Requires-Dist: threadpoolctl (==3.1.0)
Requires-Dist: typing-extensions (==4.5.0)
Requires-Dist: tzdata (==2023.3)
Requires-Dist: uvicorn (==0.22.0)
